[
    {"name": "Minecraft - Aria Math", "file": "aria-math.mp3"},
    {"name": "Minecraft - Beginning 2", "file": "beginning-2.mp3"},
    {"name": "Minecraft - Clark", "file": "clark.mp3"},
    {"name": "Minecraft - Danny", "file": "danny.mp3"},
    {"name": "Minecraft - Door", "file": "door.mp3"},
    {"name": "Minecraft - Equinoxe", "file": "equinoxe.mp3"},
    {"name": "Minecraft - Moog City 2", "file": "moog-city-2.mp3"},
    {"name": "Minecraft - Subwoofer Lullaby", "file": "subwoofer-lullaby.mp3"},
    {"name": "Minecraft - Sweden", "file": "sweden.mp3"},
    {"name": "Minecraft - Ward", "file": "ward.mp3"},
    {"name": "Minecraft - Wet Hands", "file": "wet-hands.mp3"},
    {"name": "Minecraft - Haggstrom", "file": "haggstrom.mp3"}
]